pyqmix/__init__.py
pyqmix/_version.py
pyqmix/bus.py
pyqmix/config.py
pyqmix/dio.py
pyqmix/error.py
pyqmix/headers.py
pyqmix/pump.py
pyqmix/tools.py
pyqmix/valve.py
pyqmix-2021.1.2.dist-info/LICENSE
pyqmix-2021.1.2.dist-info/METADATA
pyqmix-2021.1.2.dist-info/WHEEL
pyqmix-2021.1.2.dist-info/top_level.txt
pyqmix-2021.1.2.dist-info/RECORD
