Metadata-Version: 2.1
Name: pyqmix
Version: 2021.1.2
Summary: A wrapper for the Cetoni Qmix SDK.
Home-page: https://pyqmix.readthedocs.io/
Author: Lorenzo Alfine <lorenzo.alfine@gmail.com>, Richard Höchenberger <richard.hoechenberger@gmail.com>, Camilla Arndal Andersen <camilla@arndalandersen.dk>
Author-email: richard.hoechenberger@gmail.com
License: GPL v3
Project-URL: Source Code, https://github.com/psyfood/pyqmix/
Project-URL: Bug Tracker, https://github.com/psyfood/pyqmix/issues/
Platform: UNKNOWN
Classifier: Intended Audience :: Science/Research
Classifier: Programming Language :: Python
Classifier: Operating System :: Microsoft :: Windows
Classifier: Programming Language :: Python :: 2
Classifier: Programming Language :: Python :: 2.7
Classifier: Programming Language :: Python :: 3
Classifier: Programming Language :: Python :: 3.6
Classifier: Programming Language :: Python :: 3.7
Classifier: Programming Language :: Python :: 3.8
Classifier: Programming Language :: Python :: 3.9
